sqlutilpy/__init__.py
sqlutilpy/sqlutil.py
sqlutilpy/version.py
sqlutilpy-0.26.0.dist-info/licenses/LICENSE.txt
sqlutilpy-0.26.0.dist-info/METADATA
sqlutilpy-0.26.0.dist-info/WHEEL
sqlutilpy-0.26.0.dist-info/top_level.txt
sqlutilpy-0.26.0.dist-info/RECORD
