Metadata-Version: 2.4
Name: sqlutilpy
Version: 0.26.0
Summary: Database query code returning numpy arrays
Author-email: "Sergey E. Koposov" <skoposov@ed.ac.uk>
License: BSD
Project-URL: Homepage, https://github.com/segasai/sqlutilpy
Keywords: numpy postgresql query sql sqlite array
Classifier: Development Status :: 3 - Alpha
Classifier: License :: OSI Approved :: BSD License
Classifier: Topic :: Utilities
Requires-Python: >=3.8
License-File: LICENSE.txt
Requires-Dist: numpy
Requires-Dist: psycopg[binary]
Requires-Dist: numpydoc
Requires-Dist: numpy
Dynamic: license-file
